mlready/__init__.py
mlready/applier.py
mlready/auditor.py
mlready/exceptions.py
mlready/patterns.py
mlready/profiler.py
mlready/recipe.py
mlready/report.py
mlready/sampling.py
mlready/utils.py
mlready-0.2.1.dist-info/licenses/LICENSE
mlready-0.2.1.dist-info/METADATA
mlready-0.2.1.dist-info/WHEEL
mlready-0.2.1.dist-info/top_level.txt
mlready-0.2.1.dist-info/RECORD
