Metadata-Version: 2.4
Name: mlready
Version: 0.2.1
Summary: ML readiness auditor for tabular data with safe normalization and reproducible cleaning recipes
Author-email: Vetrivel Maheswaran <vetrim2003@gmail.com>
License: MIT
Project-URL: Homepage, https://github.com/vetrivel07/mlready
Project-URL: Repository, https://github.com/vetrivel07/mlready
Project-URL: Issues, https://github.com/vetrivel07/mlready/issues
Keywords: machine-learning,data-cleaning,data-quality,eda,ml-pipeline,data-preprocessing
Classifier: Development Status :: 3 - Alpha
Classifier: Intended Audience :: Developers
Classifier: Intended Audience :: Science/Research
Classifier: Topic :: Scientific/Engineering :: Artificial Intelligence
Classifier: Topic :: Software Development :: Libraries
Classifier: License :: OSI Approved :: MIT License
Classifier: Programming Language :: Python :: 3
Classifier: Programming Language :: Python :: 3.8
Classifier: Programming Language :: Python :: 3.9
Classifier: Programming Language :: Python :: 3.10
Classifier: Programming Language :: Python :: 3.11
Requires-Python: >=3.8
License-File: LICENSE
Requires-Dist: pandas>=1.5
Requires-Dist: numpy>=1.21
Provides-Extra: dev
Requires-Dist: pytest>=7.0; extra == "dev"
Provides-Extra: report
Requires-Dist: scikit-learn>=1.2; extra == "report"
Provides-Extra: viz
Requires-Dist: matplotlib>=3.7; extra == "viz"
Provides-Extra: full
Requires-Dist: scikit-learn>=1.2; extra == "full"
Requires-Dist: matplotlib>=3.7; extra == "full"
Dynamic: license-file
